<?xml version='1.0' encoding='UTF-8'?><magicdraw><class id="_2024x_8fe028d_1725643113170_334728_2325" refElementId="_2024x_8fe028d_1725643113170_334728_2325" humanType="Class" classType="Class" requireSort="node" icon="index_files/icon_class_1021813588.svg"><visibility humanName="Visibility" mode="e">public</visibility><templateParameter refid="_2024x_8fe028d_1725643113170_460128_2326" refElementId="_2024x_8fe028d_1725643113170_460128_2326" humanType="Classifier Template Parameter" classType="ClassifierTemplateParameter" name="K > Material_entity_kind" icon="index_files/icon_classifiertemplateparameter_1896895330.svg" humanName="Template Parameter"/><qualifiedName humanName="Qualified Name" mode="e">ENTITY::org::s2::rm::entity::physical_entity::Material_entity::K</qualifiedName><owningTemplateParameter refid="_2024x_8fe028d_1725643113170_460128_2326" refElementId="_2024x_8fe028d_1725643113170_460128_2326" humanType="Classifier Template Parameter" classType="ClassifierTemplateParameter" name="K > Material_entity_kind" icon="index_files/icon_classifiertemplateparameter_1896895330.svg" humanName="Owning Template Parameter"/><owner refid="_2024x_8fe028d_1725643113170_460128_2326" refElementId="_2024x_8fe028d_1725643113170_460128_2326" humanType="Classifier Template Parameter" classType="ClassifierTemplateParameter" name="K > Material_entity_kind" icon="index_files/icon_classifiertemplateparameter_1896895330.svg" humanName="Owner" mode="s,e"/><name humanName="Name" mode="s,e">K</name><isLeaf humanName="Is Leaf" mode="e">false</isLeaf><isFinalSpecialization humanName="Is Final Specialization" mode="e">false</isFinalSpecialization><isActive humanName="Is Active" mode="s,e">false</isActive><isAbstract humanName="Is Abstract" mode="s,e">false</isAbstract><documentation humanName="Documentation"></documentation><TO_DO humanName="To Do" mode="s,e"></TO_DO><ActiveHyperlink humanName="Active Hyperlink" mode="e"></ActiveHyperlink><report_appliedStereotype_tags humanName="Applied Stereotype" requireSort="element" mode="s,e"/></class></magicdraw>